crystflux/__init__.py
crystflux/v1/__init__.py
crystflux/v1/py.typed
crystflux/v1/adapters/__init__.py
crystflux/v1/adapters/base_chain_vesicle.py
crystflux/v1/adapters/crystallizer_impl.py
crystflux/v1/adapters/default_void_sentinel.py
crystflux/v1/adapters/desire_logger_impl.py
crystflux/v1/adapters/dream_context.py
crystflux/v1/adapters/fastapi.py
crystflux/v1/adapters/frame_inspection.py
crystflux/v1/adapters/missing_logger_impl.py
crystflux/v1/adapters/numpy.py
crystflux/v1/adapters/numpy_chain.py
crystflux/v1/adapters/numpy_chain.pyi
crystflux/v1/adapters/numpy_chain_modes.py
crystflux/v1/adapters/pydantic.py
crystflux/v1/adapters/sentinel_to_cryst.py
crystflux/v1/boundary/__init__.py
crystflux/v1/boundary/chain_context.py
crystflux/v1/boundary/chain_step.py
crystflux/v1/boundary/crystallizer_port.py
crystflux/v1/boundary/desire_logger.py
crystflux/v1/boundary/error_contracts.py
crystflux/v1/boundary/event_schema.py
crystflux/v1/boundary/missing_logger.py
crystflux/v1/boundary/mode_contracts.py
crystflux/v1/boundary/vesicle_api.py
crystflux/v1/boundary/void_sentinel.py
crystflux/v1/core/__init__.py
crystflux/v1/core/freeze_value.py
crystflux/v1/core/json_types.py
crystflux/v1/core/value_api.py
crystflux/v1/core/value_array.py
crystflux/v1/core/value_core.py
crystflux/v1/core/value_modes.py
crystflux/v1/core/value_projections.py
crystflux/v1/core/void_reason.py
crystflux/v1/core/void_value.py
crystflux-0.23.10.dist-info/licenses/LICENSE
crystflux-0.23.10.dist-info/METADATA
crystflux-0.23.10.dist-info/WHEEL
crystflux-0.23.10.dist-info/top_level.txt
crystflux-0.23.10.dist-info/RECORD
