Metadata-Version: 2.4
Name: crystflux
Version: 0.23.10
Summary: A type-safe immutable JSON toolkit with chainable method access.
Author-email: "T.K" <the.usefulness.of.the.useless@gmail.com>
License-Expression: MIT
Project-URL: Repository, https://github.com/void-latent/crystflux
Classifier: Development Status :: 4 - Beta
Classifier: Intended Audience :: Developers
Classifier: Operating System :: OS Independent
Classifier: Programming Language :: Python :: 3.11
Classifier: Topic :: Software Development :: Libraries
Classifier: Topic :: Utilities
Requires-Python: >=3.11
License-File: LICENSE
Provides-Extra: numpy
Requires-Dist: numpy>=2.3; extra == "numpy"
Provides-Extra: pydantic
Requires-Dist: pydantic; extra == "pydantic"
Provides-Extra: dev
Requires-Dist: pytest; extra == "dev"
Requires-Dist: pytest-cov; extra == "dev"
Requires-Dist: ruff; extra == "dev"
Requires-Dist: basedpyright; extra == "dev"
Requires-Dist: mypy; extra == "dev"
Provides-Extra: all
Requires-Dist: crystflux[numpy]; extra == "all"
Requires-Dist: crystflux[pydantic]; extra == "all"
Dynamic: license-file
